ltspice_to_svg-0.2.0.dist-info/licenses/LICENSE
src/__init__.py
src/ltspice_to_svg.py
src/parsers/__init__.py
src/parsers/asc_parser.py
src/parsers/asy_parser.py
src/parsers/schematic_parser.py
src/parsers/shape_parser.py
src/renderers/base_renderer.py
src/renderers/flag_renderer.py
src/renderers/rendering_config.py
src/renderers/shape_renderer.py
src/renderers/svg_renderer.py
src/renderers/symbol_renderer.py
src/renderers/text_renderer.py
src/renderers/viewbox_calculator.py
src/renderers/wire_renderer.py
src/renderers/flag_definitions/flags.json
ltspice_to_svg-0.2.0.dist-info/METADATA
ltspice_to_svg-0.2.0.dist-info/WHEEL
ltspice_to_svg-0.2.0.dist-info/entry_points.txt
ltspice_to_svg-0.2.0.dist-info/top_level.txt
ltspice_to_svg-0.2.0.dist-info/RECORD
