Metadata-Version: 2.4
Name: ltspice_to_svg
Version: 0.2.0
Summary: Convert LTspice schematics to SVG format
Home-page: https://github.com/Jianxun/ltspice_to_svg
Author: Jianxun Zhu
Author-email: zhujianxun.bupt@gmail.com
License-Expression: MIT
Keywords: ltspice,svg,schematic,circuit,eda,electronics
Classifier: Development Status :: 4 - Beta
Classifier: Intended Audience :: Science/Research
Classifier: Programming Language :: Python :: 3
Classifier: Topic :: Scientific/Engineering :: Electronic Design Automation (EDA)
Classifier: Programming Language :: Python :: 3.6
Classifier: Programming Language :: Python :: 3.7
Classifier: Programming Language :: Python :: 3.8
Classifier: Programming Language :: Python :: 3.9
Classifier: Programming Language :: Python :: 3.10
Classifier: Programming Language :: Python :: 3.11
Classifier: Programming Language :: Python :: 3.12
Requires-Python: >=3.6
License-File: LICENSE
Requires-Dist: svgwrite
Dynamic: author
Dynamic: author-email
Dynamic: classifier
Dynamic: home-page
Dynamic: keywords
Dynamic: license-file
Dynamic: requires-dist
Dynamic: requires-python
